secmgr/__main__.py
secmgr-1.0.7.dist-info/LICENSE
secmgr-1.0.7.dist-info/WHEEL
secmgr-1.0.7.dist-info/METADATA
secmgr-1.0.7.dist-info/RECORD
