Metadata-Version: 2.1
Name: secmgr
Version: 1.0.7
Summary: Utility for working with AWS Secrets Manager
License: MIT
Author: Naveed Khan
Author-email: naveed@kinoo.family
Requires-Python: >=3.8,<4.0
Classifier: License :: OSI Approved :: MIT License
Classifier: Programming Language :: Python :: 3
Classifier: Programming Language :: Python :: 3.8
Classifier: Programming Language :: Python :: 3.9
Requires-Dist: boto3 (>=1.16.25,<2.0.0)
